README.txt
setup.py
zaguan_inspector/__init__.py
zaguan_inspector.egg-info/PKG-INFO
zaguan_inspector.egg-info/SOURCES.txt
zaguan_inspector.egg-info/dependency_links.txt
zaguan_inspector.egg-info/requires.txt
zaguan_inspector.egg-info/top_level.txt