Metadata-Version: 1.0
Name: zaguan-inspector
Version: 0.1.0
Summary: Webkit inspector for Zaguan
Home-page: http://pypi.python.org/pypi/zaguan_inspector/
Author: Felipe Lerena
Author-email: flerena@msa.com.ar
License: LICENSE.txt
Platform: UNKNOWN
